customtkinterx/__base64.py
customtkinterx/__init__.py
customtkinterx/__main__.py
customtkinterx/CTkCustom.py
customtkinterx/CTkCustomBorder.py
customtkinterx/CTkFluentTheme.py
customtkinterx/CTkGhostSharkTheme.py
customtkinterx/CTkInfoBar.py
customtkinterx/CTkKanban.py
customtkinterx/CTkListBox.py
customtkinterx/CTkMaterialTheme.py
customtkinterx/CTkMegaMenuBar.py
customtkinterx/CTkMenuBar/__init__.py
customtkinterx/CTkMenuBar/dropdown_menu.py
customtkinterx/CTkMenuBar/menu_bar.py
customtkinterx/CTkMenuBar/title_menu_win.py
customtkinterx/CTkMinimalTheme.py
customtkinterx/CTkOffice2019Theme.py
customtkinterx/CTkPDFViewer/__init__.py
customtkinterx/CTkPDFViewer/ctk_pdf_viewer.py
customtkinterx/CTkSnackBar.py
customtkinterx/CTkStack.py
customtkinterx/CTkTable/__init__.py
customtkinterx/CTkTable/ctktable.py
customtkinterx/CTkToolTip/__init__.py
customtkinterx/CTkToolTip/ctk_tooltip.py
customtkinterx/Fluent.json
customtkinterx/fluent_android/__init__.py
customtkinterx/fluent_android/CTkFluentAndroidTheme.py
customtkinterx/fluent_android/CTkFluentAppBar.py
customtkinterx/fluent_android/FluentAndroid.json
customtkinterx/GhostShark.json
customtkinterx/LaunchMusix.py
customtkinterx/Material.json
customtkinterx/Minimal.json
customtkinterx/Musix-Dark.png
customtkinterx/Musix.png
customtkinterx/Office2019.json
customtkinterx/PublicSans-Regular.ttf
customtkinterx/test.py
customtkinterx-0.4.4.dist-info/METADATA
customtkinterx-0.4.4.dist-info/WHEEL
customtkinterx-0.4.4.dist-info/RECORD
