Metadata-Version: 2.1
Name: customtkinterx
Version: 0.4.4
Summary: extra widgets for customtkinter
Author: XiangQinxi
Author-email: XiangQinxi@outlook.com
Requires-Python: >=3.7,<4.0
Classifier: Programming Language :: Python :: 3
Classifier: Programming Language :: Python :: 3.7
Classifier: Programming Language :: Python :: 3.8
Classifier: Programming Language :: Python :: 3.9
Classifier: Programming Language :: Python :: 3.10
Classifier: Programming Language :: Python :: 3.11
Requires-Dist: customtkinter (>=5.1.3,<6.0.0)
